[{
  "_id": {
    "$oid": "60d635c1bc581903d4df5443"
  },
  "departement": [],
  "nom_filiere": "SEM",
  "niveau": "A",
  "__v": 0
},{
  "_id": {
    "$oid": "60d635cebc581903d4df5444"
  },
  "departement": [],
  "nom_filiere": "DSI",
  "niveau": "A",
  "__v": 0
},{
  "_id": {
    "$oid": "60d635d8bc581903d4df5445"
  },
  "departement": [],
  "nom_filiere": "MDW",
  "niveau": "A",
  "__v": 0
},{
  "_id": {
    "$oid": "60d635debc581903d4df5446"
  },
  "departement": [],
  "nom_filiere": "RSI",
  "niveau": "A",
  "__v": 0
},{
  "_id": {
    "$oid": "60d635e4bc581903d4df5447"
  },
  "departement": [],
  "nom_filiere": "AA",
  "niveau": "A",
  "__v": 0
}]